[
  {
    "title": "내년 서울국제정원박람회는 서울숲·매헌시민의숲서…최대규모(종합)",
    "url": "https://www.yna.co.kr/view/AKR20251103018451004?input=1195m"
  },
  {
    "title": "尹 모교 축제서 울려 퍼진 \"윤 어게인\"...논란 커지자 사과",
    "url": "https://www.ytn.co.kr/_ln/0103_202511031445283344"
  },
  {
    "title": "충암고 축제서 “윤 어게인!”…‘동문’ 래퍼, 결국 사과",
    "url": "https://www.hani.co.kr/arti/society/society_general/1226859.html"
  },
  {
    "title": "노원, 19개 동 마을축제 및 주민총회 개최",
    "url": "https://biz.heraldcorp.com/article/10607991?ref=naver"
  },
  {
    "title": "데상트, 러닝 축제 '러너스 데이' 마무리",
    "url": "http://www.enewstoday.co.kr/news/articleView.html?idxno=2349342"
  },
  {
    "title": "서울 중구 동화동서 8일 '가을동화축제' 열린다",
    "url": "https://www.yna.co.kr/view/AKR20251104013300004?input=1195m"
  },
  {
    "title": "\"어린이가 예술로 행복한 세상\"…아르코, 나주서 가을 예술축제 연다",
    "url": "https://www.news1.kr/life-culture/performance-exhibition/5963833"
  },
  {
    "title": "래퍼 정상수, 충암고 축제서 \"尹 어게인\" 외쳐…학생회 \"개인적 발언\"",
    "url": "https://www.newsis.com/view/NISX20251101_0003386315"
  },
  {
    "title": "영주사과, 서울시민 입맛 사로잡다… 첫 진상축제서 인기",
    "url": "https://view.asiae.co.kr/article/2025110310380505351"
  },
  {
    "title": "멋진 로봇 말과 사이버트럭 보고싶다면···양재 ‘말죽거리 축제’로...",
    "url": "https://www.khan.co.kr/article/202511031124021"
  }
]